{
  "RequestId": "req-winget-vscode-msstore",
  "CreatedAt": "2026-05-05T12:18:00Z",
  "Operation": "Install",
  "Manager": {
    "Name": "Winget",
    "DisplayName": "WinGet",
    "ExecutableFriendlyName": "winget.exe"
  },
  "Source": {
    "Name": "msstore",
    "Url": "https://storeedgefd.dsx.mp.microsoft.com/v9.0",
    "IsVirtualManager": false
  },
  "Package": {
    "Id": "Microsoft.VisualStudioCode",
    "Name": "Microsoft Visual Studio Code",
    "Architecture": "X64"
  },
  "Options": {
    "Scope": "User",
    "Interactive": false,
    "SkipHashCheck": false,
    "PreRelease": false,
    "CustomParameters": [],
    "KillBeforeOperation": []
  },
  "Broker": {
    "RequestedElevation": "Standard",
    "EffectiveUser": "CONTOSO\\alice",
    "ClientVersion": "3.2.0"
  }
}
